eric_lang/lang.py
eric_lang-0.0.5.dist-info/METADATA
eric_lang-0.0.5.dist-info/WHEEL
eric_lang-0.0.5.dist-info/entry_points.txt
eric_lang-0.0.5.dist-info/top_level.txt
eric_lang-0.0.5.dist-info/RECORD
