Metadata-Version: 2.1
Name: eric-lang
Version: 0.0.5
Summary: My own langugae
Author-email: Eric Hurst <eric.hurst97@gmail.com>
Requires-Python: >=3.7
